account/__init__.py
account/first.py
new_account-0.2.dist-info/License.txt
new_account-0.2.dist-info/METADATA
new_account-0.2.dist-info/WHEEL
new_account-0.2.dist-info/top_level.txt
new_account-0.2.dist-info/RECORD
