Metadata-Version: 2.1
Name: new-account
Version: 0.2
Summary: OOP-based bank system
Author: Prathamesh72
Author-email: pspwork72@gmail.com
License: MIT
License-File: License.txt
Requires-Dist: pandas
